applecatalog/__init__.py
applecatalog/__main__.py
applecatalog/_version.py
applecatalog/catalog.py
applecatalog-3.0.1.dist-info/METADATA
applecatalog-3.0.1.dist-info/WHEEL
applecatalog-3.0.1.dist-info/entry_points.txt
applecatalog-3.0.1.dist-info/top_level.txt
applecatalog-3.0.1.dist-info/RECORD
