Metadata-Version: 2.4
Name: applecatalog
Version: 3.0.1
Summary: AppleCatalog download agent
Author-email: doronz88 <doron88@gmail.com>
Maintainer-email: doronz88 <doron88@gmail.com>
Project-URL: Homepage, https://github.com/doronz88/applecatalog
Project-URL: Bug Reports, https://github.com/doronz88/applecatalog/issues
Keywords: apple,download,automations,updates
Classifier: Development Status :: 5 - Production/Stable
Classifier: License :: OSI Approved :: GNU General Public License v3 or later (GPLv3+)
Classifier: Programming Language :: Python :: 3
Classifier: Programming Language :: Python :: 3.10
Classifier: Programming Language :: Python :: 3.11
Classifier: Programming Language :: Python :: 3.12
Classifier: Programming Language :: Python :: 3.13
Classifier: Programming Language :: Python :: 3.14
Classifier: Programming Language :: Python :: 3 :: Only
Requires-Python: >=3.10
Requires-Dist: coloredlogs
Requires-Dist: tqdm
Requires-Dist: click
Requires-Dist: requests
Provides-Extra: test
Requires-Dist: pytest; extra == "test"
